MANIFEST.in
README.md
VERSION
setup.py
../LICENSE
kadalu_quotad/__init__.py
kadalu_quotad/glusterutils.py
kadalu_quotad/kadalulib.py
kadalu_quotad/quotad.py
kadalu_quotad.egg-info/PKG-INFO
kadalu_quotad.egg-info/SOURCES.txt
kadalu_quotad.egg-info/dependency_links.txt
kadalu_quotad.egg-info/entry_points.txt
kadalu_quotad.egg-info/not-zip-safe
kadalu_quotad.egg-info/requires.txt
kadalu_quotad.egg-info/top_level.txt